saer/__init__.py
saer_openapi-1.3.2.dist-info/LICENSE
saer_openapi-1.3.2.dist-info/METADATA
saer_openapi-1.3.2.dist-info/WHEEL
saer_openapi-1.3.2.dist-info/top_level.txt
saer_openapi-1.3.2.dist-info/RECORD
