Metadata-Version: 2.1
Name: saer-openapi
Version: 1.3.2
Summary: A python sdk for [SAER-OPENAPI](http://api.isaerdata.com/)
Home-page: https://github.com/Haoke98/saer-openapi-sdk
Author-email: Sadam·Sadik <Haoke98@outlook.com>
Maintainer-email: Sadam·Sadik <Haoke98@outlook.com>
License: Apache License
Project-URL: Homepage, https://github.com/Haoke98/saer-openapi-sdk
Project-URL: Documentation, https://github.com/Haoke98/saer-openapi-sdk/README.md
Project-URL: Repository, https://github.com/Haoke98/saer-openapi-sdk.git
Project-URL: Bug Tracker, https://github.com/Haoke98/saer-openapi-sdk/issues
Project-URL: API Documentation, http://api.isaerdata.com/
Project-URL: Changelog, https://github.com/Haoke98/saer-openapi-sdk/releases
Keywords: saer,openapi,api,sdk,python-sdk,api.isaerdata.com
Classifier: Development Status :: 5 - Production/Stable
Classifier: Environment :: Console
Classifier: Intended Audience :: Developers
Classifier: Intended Audience :: Information Technology
Classifier: License :: OSI Approved :: Apache Software License
Classifier: Natural Language :: English
Classifier: Operating System :: OS Independent
Classifier: Programming Language :: Python :: 3.11
Classifier: Programming Language :: Python :: 3.10
Classifier: Programming Language :: Python :: 3.9
Classifier: Programming Language :: Python :: 3.8
Classifier: Programming Language :: Python :: 3.7
Classifier: Programming Language :: Python :: 3.6
Classifier: Topic :: Internet :: WWW/HTTP :: Indexing/Search
Classifier: Topic :: Scientific/Engineering :: Interface Engine/Protocol Translator
Requires-Python: >=3.6
License-File: LICENSE
Requires-Dist: requests >=2.27.0
